{"surah":67,"verses":[{"n":1,"key":"67:1","arabic":" تَبَـٰرَكَ ٱلَّذِى بِيَدِهِ ٱلْمُلْكُ وَهُوَ عَلَىٰ كُلِّ شَىْءٍ قَدِيرٌ","page":562,"juz":29,"en":"Blessed is He in whose hand is dominion, and He is over all things competent -","id":"Mahasuci Allah yang menguasai (segala) kerajaan, Dan Dia Mahakuasa atas segala sesuatu.","words":[{"a":"تَبَـٰرَكَ","en":"Blessed is","id":"Maha Suci"},{"a":"ٱلَّذِى","en":"He","id":"yang"},{"a":"بِيَدِهِ","en":"in Whose Hand","id":"di tangan-Nya"},{"a":"ٱلْمُلْكُ","en":"(is) the Dominion","id":"kerajaan"},{"a":"وَهُوَ","en":"and He","id":"dan Dia"},{"a":"عَلَىٰ","en":"(is) over","id":"atas"},{"a":"كُلِّ","en":"every","id":"segala"},{"a":"شَىْءٍۢ","en":"thing","id":"sesuatu"},{"a":"قَدِيرٌ","en":"All-Powerful","id":"Maha Kuasa"}]},{"n":2,"key":"67:2","arabic":"ٱلَّذِى خَلَقَ ٱلْمَوْتَ وَٱلْحَيَوٰةَ لِيَبْلُوَكُمْ أَيُّكُمْ أَحْسَنُ عَمَلًا ۚ وَهُوَ ٱلْعَزِيزُ ٱلْغَفُورُ","page":562,"juz":29,"en":"[He] who created death and life to test you [as to] which of you is best in deed - and He is the Exalted in Might, the Forgiving -","id":"Yang menciptakan mati dan hidup, untuk menguji kamu, siapa di antara kamu yang lebih baik amalnya. Dan Dia Mahaperkasa, Maha Pengampun.","words":[{"a":"ٱلَّذِى","en":"The One Who","id":"yang"},{"a":"خَلَقَ","en":"created","id":"menciptakan"},{"a":"ٱلْمَوْتَ","en":"death","id":"kematian"},{"a":"وَٱلْحَيَوٰةَ","en":"and life","id":"dan kehidupan"},{"a":"لِيَبْلُوَكُمْ","en":"that He may test you","id":"karena Dia akan mengujimu"},{"a":"أَيُّكُمْ","en":"which of you","id":"siapa diantara kamu"},{"a":"أَحْسَنُ","en":"(is) best","id":"lebih baik"},{"a":"عَمَلًۭا ۚ","en":"(in) deed","id":"perbuatan"},{"a":"وَهُوَ","en":"And He","id":"dan Dia"},{"a":"ٱلْعَزِيزُ","en":"(is) the All-Mighty","id":"Maha Perkasa"},{"a":"ٱلْغَفُورُ","en":"the Oft-Forgiving","id":"Maha Pengampun"}]},{"n":3,"key":"67:3","arabic":"ٱلَّذِى خَلَقَ سَبْعَ سَمَـٰوَٰتٍ طِبَاقًا ۖ مَّا تَرَىٰ فِى خَلْقِ ٱلرَّحْمَـٰنِ مِن تَفَـٰوُتٍ ۖ فَٱرْجِعِ ٱلْبَصَرَ هَلْ تَرَىٰ مِن فُطُورٍ","page":562,"juz":29,"en":"[And] who created seven heavens in layers. You do not see in the creation of the Most Merciful any inconsistency. So return [your] vision [to the sky]; do you see any breaks?","id":"Yang menciptakan tujuh langit berlapis-lapis. Tidak akan kamu lihat sesuatu yang tidak seimbang pada ciptaan Tuhan Yang Maha Pengasih. Maka lihatlah sekali lagi, adakah kamu lihat sesuatu yang cacat?","words":[{"a":"ٱلَّذِى","en":"The One Who","id":"yang"},{"a":"خَلَقَ","en":"created","id":"menciptakan"},{"a":"سَبْعَ","en":"seven","id":"tujuh"},{"a":"سَمَـٰوَٰتٍۢ","en":"heavens","id":"langit"},{"a":"طِبَاقًۭا ۖ","en":"one above another","id":"berlapis-lapis"},{"a":"مَّا","en":"Not","id":"tidak"},{"a":"تَرَىٰ","en":"you see","id":"kamu lihat"},{"a":"فِى","en":"in","id":"dalam/pada"},{"a":"خَلْقِ","en":"(the) creation","id":"penciptaan"},{"a":"ٱلرَّحْمَـٰنِ","en":"(of) the Most Gracious","id":"Yang Maha Pengasih"},{"a":"مِن","en":"any","id":"dari"},{"a":"تَفَـٰوُتٍۢ ۖ","en":"fault","id":"tidak seimbang"},{"a":"فَٱرْجِعِ","en":"So return","id":"maka kembalilah"},{"a":"ٱلْبَصَرَ","en":"the vision","id":"pandangan"},{"a":"هَلْ","en":"can","id":"apakah"},{"a":"تَرَىٰ","en":"you see","id":"kamu melihat"},{"a":"مِن","en":"any","id":"dari"},{"a":"فُطُورٍۢ","en":"flaw","id":"teratur/seimbang"}]},{"n":4,"key":"67:4","arabic":"ثُمَّ ٱرْجِعِ ٱلْبَصَرَ كَرَّتَيْنِ يَنقَلِبْ إِلَيْكَ ٱلْبَصَرُ خَاسِئًا وَهُوَ حَسِيرٌ","page":562,"juz":29,"en":"Then return [your] vision twice again. [Your] vision will return to you humbled while it is fatigued.","id":"Kemudian ulangi pandangan(mu) sekali lagi (dan) sekali lagi, niscaya pandanganmu akan kembali kepadamu tanpa menemukan cacat dan ia (pandanganmu) dalam keadaan letih.","words":[{"a":"ثُمَّ","en":"Then","id":"kemudian"},{"a":"ٱرْجِعِ","en":"return","id":"kembalilah"},{"a":"ٱلْبَصَرَ","en":"the vision","id":"pandangan"},{"a":"كَرَّتَيْنِ","en":"twice (again)","id":"dua kali ulang"},{"a":"يَنقَلِبْ","en":"Will return","id":"berbalik/kembali"},{"a":"إِلَيْكَ","en":"to you","id":"kepadamu"},{"a":"ٱلْبَصَرُ","en":"the vision","id":"pandangan"},{"a":"خَاسِئًۭا","en":"humbled","id":"membingungkan"},{"a":"وَهُوَ","en":"while it","id":"dan ia"},{"a":"حَسِيرٌۭ","en":"(is) fatigued","id":"lemah"}]},{"n":5,"key":"67:5","arabic":"وَلَقَدْ زَيَّنَّا ٱلسَّمَآءَ ٱلدُّنْيَا بِمَصَـٰبِيحَ وَجَعَلْنَـٰهَا رُجُومًا لِّلشَّيَـٰطِينِ ۖ وَأَعْتَدْنَا لَهُمْ عَذَابَ ٱلسَّعِيرِ","page":562,"juz":29,"en":"And We have certainly beautified the nearest heaven with lamps [i.e., stars] and have made [from] them what is thrown at the devils and have prepared for them the punishment of the Blaze.","id":"Dan sungguh, telah Kami hiasi langit yang dekat, dengan bintang-bintang dan Kami jadikannya (bintang-bintang itu) sebagai alat-alat pelempar setan, dan Kami sediakan bagi mereka azab neraka yang menyala-nyala.","words":[{"a":"وَلَقَدْ","en":"And certainly","id":"dan sesungguhnya"},{"a":"زَيَّنَّا","en":"We have beautified","id":"Kami menghiasi"},{"a":"ٱلسَّمَآءَ","en":"the heaven","id":"langit"},{"a":"ٱلدُّنْيَا","en":"nearest","id":"dunia/yang dekat"},{"a":"بِمَصَـٰبِيحَ","en":"with lamps","id":"dengan bintang-bintang"},{"a":"وَجَعَلْنَـٰهَا","en":"and We have made them","id":"dan Kami menjadikannya"},{"a":"رُجُومًۭا","en":"(as) missiles","id":"pelempar"},{"a":"لِّلشَّيَـٰطِينِ ۖ","en":"for the devils","id":"terhadap syaitan-syaitan"},{"a":"وَأَعْتَدْنَا","en":"and We have prepared","id":"dan Kami sediakan"},{"a":"لَهُمْ","en":"for them","id":"bagi mereka"},{"a":"عَذَابَ","en":"punishment","id":"azab/siksa"},{"a":"ٱلسَّعِيرِ","en":"(of) the Blaze","id":"neraka yang menyala-nyala"}]},{"n":6,"key":"67:6","arabic":"وَلِلَّذِينَ كَفَرُوا۟ بِرَبِّهِمْ عَذَابُ جَهَنَّمَ ۖ وَبِئْسَ ٱلْمَصِيرُ","page":562,"juz":29,"en":"And for those who disbelieved in their Lord is the punishment of Hell, and wretched is the destination.","id":"Dan orang-orang yang ingkar kepada Tuhannya, akan mendapat azab Jahanam. Dan itulah seburuk-buruk tempat kembali.","words":[{"a":"وَلِلَّذِينَ","en":"And for those who","id":"dan bagi orang-orang yang"},{"a":"كَفَرُوا۟","en":"disbelieved","id":"kafir/ingkar"},{"a":"بِرَبِّهِمْ","en":"in their Lord","id":"kepada Tuhan mereka"},{"a":"عَذَابُ","en":"(is the) punishment","id":"azab/siksa"},{"a":"جَهَنَّمَ ۖ","en":"(of) Hell","id":"neraka jahannam"},{"a":"وَبِئْسَ","en":"and wretched is","id":"dan amat buruk"},{"a":"ٱلْمَصِيرُ","en":"the destination","id":"tempat kembali"}]},{"n":7,"key":"67:7","arabic":"إِذَآ أُلْقُوا۟ فِيهَا سَمِعُوا۟ لَهَا شَهِيقًا وَهِىَ تَفُورُ","page":562,"juz":29,"en":"When they are thrown into it, they hear from it a [dreadful] inhaling while it boils up.","id":"Apabila mereka dilemparkan ke dalamnya mereka mendengar suara neraka yang mengerikan, sedang neraka itu membara,","words":[{"a":"إِذَآ","en":"When","id":"apabila"},{"a":"أُلْقُوا۟","en":"they are thrown","id":"mereka dilemparkan"},{"a":"فِيهَا","en":"therein","id":"di dalamnya"},{"a":"سَمِعُوا۟","en":"they will hear","id":"mereka mendengar"},{"a":"لَهَا","en":"from it","id":"baginya"},{"a":"شَهِيقًۭا","en":"an inhaling","id":"jeritan"},{"a":"وَهِىَ","en":"while it","id":"dan ia"},{"a":"تَفُورُ","en":"boils up","id":"mendidih"}]},{"n":8,"key":"67:8","arabic":"تَكَادُ تَمَيَّزُ مِنَ ٱلْغَيْظِ ۖ كُلَّمَآ أُلْقِىَ فِيهَا فَوْجٌ سَأَلَهُمْ خَزَنَتُهَآ أَلَمْ يَأْتِكُمْ نَذِيرٌ","page":562,"juz":29,"en":"It almost bursts with rage. Every time a company is thrown into it, its keepers ask them, \"Did there not come to you a warner?\"","id":"hampir meledak karena marah. Setiap kali ada sekumpulan (orang-orang kafir) dilemparkan ke dalamnya, penjaga-penjaga (neraka itu) bertanya kepada mereka, \"Apakah belum pernah ada orang yang datang memberi peringatan kepadamu (di dunia)?\"","words":[{"a":"تَكَادُ","en":"It almost","id":"hampir-hampir"},{"a":"تَمَيَّزُ","en":"bursts","id":"terpecah belah"},{"a":"مِنَ","en":"from","id":"dari"},{"a":"ٱلْغَيْظِ ۖ","en":"rage","id":"lantaran marah"},{"a":"كُلَّمَآ","en":"Every time","id":"setiap kali"},{"a":"أُلْقِىَ","en":"is thrown","id":"dilempar"},{"a":"فِيهَا","en":"therein","id":"di dalamnya"},{"a":"فَوْجٌۭ","en":"a group","id":"sekumpulan"},{"a":"سَأَلَهُمْ","en":"(will) ask them","id":"bertanya kepada mereka"},{"a":"خَزَنَتُهَآ","en":"its keepers","id":"penjaga-penjaganya"},{"a":"أَلَمْ","en":"Did not","id":"apakah tidak"},{"a":"يَأْتِكُمْ","en":"come to you","id":"datang kepadamu"},{"a":"نَذِيرٌۭ","en":"a warner","id":"seorang pemberi peringatan"}]},{"n":9,"key":"67:9","arabic":"قَالُوا۟ بَلَىٰ قَدْ جَآءَنَا نَذِيرٌ فَكَذَّبْنَا وَقُلْنَا مَا نَزَّلَ ٱللَّهُ مِن شَىْءٍ إِنْ أَنتُمْ إِلَّا فِى ضَلَـٰلٍ كَبِيرٍ","page":562,"juz":29,"en":"They will say, \"Yes, a warner had come to us, but we denied and said, 'Allāh has not sent down anything. You are not but in great error.'\"","id":"Mereka menjawab, \"Benar, sungguh, seorang pemberi peringatan telah datang kepada kami, tetapi kami mendustakan(nya) dan kami katakan, \"Allah tidak menurunkan sesuatu apa pun, kamu sebenarnya di dalam kesesatan yang besar.\"","words":[{"a":"قَالُوا۟","en":"They will say","id":"mereka berkata/menjawab"},{"a":"بَلَىٰ","en":"Yes","id":"ya benar"},{"a":"قَدْ","en":"indeed","id":"sesungguhnya"},{"a":"جَآءَنَا","en":"came to us","id":"telah datang kepada kami"},{"a":"نَذِيرٌۭ","en":"a warner","id":"seorang pemberi peringatan"},{"a":"فَكَذَّبْنَا","en":"but we denied","id":"maka kami mendustakan"},{"a":"وَقُلْنَا","en":"and we said","id":"dan kami katakan"},{"a":"مَا","en":"Not","id":"tidak"},{"a":"نَزَّلَ","en":"has sent down","id":"menurunkan"},{"a":"ٱللَّهُ","en":"Allah","id":"Allah"},{"a":"مِن","en":"any","id":"dari"},{"a":"شَىْءٍ","en":"thing","id":"sesuatu"},{"a":"إِنْ","en":"Not","id":"tidaklah"},{"a":"أَنتُمْ","en":"you (are)","id":"kamu"},{"a":"إِلَّا","en":"but","id":"kecuali"},{"a":"فِى","en":"in","id":"dalam"},{"a":"ضَلَـٰلٍۢ","en":"error","id":"kesesatan"},{"a":"كَبِيرٍۢ","en":"great","id":"besar"}]},{"n":10,"key":"67:10","arabic":"وَقَالُوا۟ لَوْ كُنَّا نَسْمَعُ أَوْ نَعْقِلُ مَا كُنَّا فِىٓ أَصْحَـٰبِ ٱلسَّعِيرِ","page":562,"juz":29,"en":"And they will say, \"If only we had been listening or reasoning, we would not be among the companions of the Blaze.\"","id":"Dan mereka berkata, \"Sekiranya (dahulu) kami mendengarkan atau memikirkan (peringatan itu) tentulah kami tidak termasuk penghuni neraka yang menyala-nyala.\"","words":[{"a":"وَقَالُوا۟","en":"And they will say","id":"dan mereka berkata"},{"a":"لَوْ","en":"If","id":"sekiranya"},{"a":"كُنَّا","en":"we had","id":"adalah kami"},{"a":"نَسْمَعُ","en":"listened","id":"kami mendengarkan"},{"a":"أَوْ","en":"or","id":"atau"},{"a":"نَعْقِلُ","en":"reasoned","id":"kami berakal"},{"a":"مَا","en":"not","id":"tidaklah"},{"a":"كُنَّا","en":"we (would) have been","id":"kami"},{"a":"فِىٓ","en":"among","id":"dalam"},{"a":"أَصْحَـٰبِ","en":"(the) companions","id":"penghuni"},{"a":"ٱلسَّعِيرِ","en":"(of) the Blaze","id":"neraka yang menyala-nyala"}]},{"n":11,"key":"67:11","arabic":"فَٱعْتَرَفُوا۟ بِذَنۢبِهِمْ فَسُحْقًا لِّأَصْحَـٰبِ ٱلسَّعِيرِ","page":562,"juz":29,"en":"And they will admit their sin, so [it is] alienation for the companions of the Blaze.","id":"Maka mereka mengakui dosanya. Tetapi jauhlah (dari rahmat Allah) bagi penghuni neraka yang menyala-nyala itu.","words":[{"a":"فَٱعْتَرَفُوا۟","en":"Then they (will) confess","id":"maka mereka mengakui"},{"a":"بِذَنۢبِهِمْ","en":"their sins","id":"dengan/akan dosa mereka"},{"a":"فَسُحْقًۭا","en":"so away with","id":"maka kebinasaanlah"},{"a":"لِّأَصْحَـٰبِ","en":"(the) companions","id":"bagi penghuni"},{"a":"ٱلسَّعِيرِ","en":"(of) the Blaze","id":"neraka yang menyala-nyala"}]},{"n":12,"key":"67:12","arabic":"إِنَّ ٱلَّذِينَ يَخْشَوْنَ رَبَّهُم بِٱلْغَيْبِ لَهُم مَّغْفِرَةٌ وَأَجْرٌ كَبِيرٌ","page":562,"juz":29,"en":"Indeed, those who fear their Lord unseen will have forgiveness and great reward.","id":"Sesungguhnya orang-orang yang takut kepada Tuhannya yang tidak terlihat oleh mereka, mereka memperoleh ampunan dan pahala yang besar.","words":[{"a":"إِنَّ","en":"Indeed","id":"sesungguhnya"},{"a":"ٱلَّذِينَ","en":"those who","id":"orang-orang yang"},{"a":"يَخْشَوْنَ","en":"fear","id":"mereka takut"},{"a":"رَبَّهُم","en":"their Lord","id":"Tuhan mereka"},{"a":"بِٱلْغَيْبِ","en":"unseen","id":"dengan gaib/tidak kelihatan"},{"a":"لَهُم","en":"for them","id":"bagi mereka"},{"a":"مَّغْفِرَةٌۭ","en":"(is) forgiveness","id":"ampunan"},{"a":"وَأَجْرٌۭ","en":"and a reward","id":"dan pahala"},{"a":"كَبِيرٌۭ","en":"great","id":"besar"}]},{"n":13,"key":"67:13","arabic":"وَأَسِرُّوا۟ قَوْلَكُمْ أَوِ ٱجْهَرُوا۟ بِهِۦٓ ۖ إِنَّهُۥ عَلِيمٌۢ بِذَاتِ ٱلصُّدُورِ","page":563,"juz":29,"en":"And conceal your speech or publicize it; indeed, He is Knowing of that within the breasts.","id":"Dan rahasiakanlah perkataanmu atau nyatakanlah. Sungguh, Dia Maha Mengetahui segala isi hati.","words":[{"a":"وَأَسِرُّوا۟","en":"And conceal","id":"dan rahasiakanlah"},{"a":"قَوْلَكُمْ","en":"your speech","id":"perkataanmu"},{"a":"أَوِ","en":"or","id":"atau"},{"a":"ٱجْهَرُوا۟","en":"proclaim","id":"keraskanlah"},{"a":"بِهِۦٓ ۖ","en":"it","id":"dengannya"},{"a":"إِنَّهُۥ","en":"Indeed, He","id":"sesungguhnya Dia"},{"a":"عَلِيمٌۢ","en":"(is the) All-Knower","id":"Maha mengetahui"},{"a":"بِذَاتِ","en":"of what (is in)","id":"dengan yang ada"},{"a":"ٱلصُّدُورِ","en":"the breasts","id":"dada"}]},{"n":14,"key":"67:14","arabic":"أَلَا يَعْلَمُ مَنْ خَلَقَ وَهُوَ ٱللَّطِيفُ ٱلْخَبِيرُ","page":563,"juz":29,"en":"Does He who created not know, while He is the Subtle, the Aware?","id":"Apakah (pantas) Allah yang menciptakan itu tidak mengetahui? Dan Dia Mahahalus, Maha Mengetahui.","words":[{"a":"أَلَا","en":"Does not","id":"apakah tidak/tidakkah"},{"a":"يَعْلَمُ","en":"know","id":"Dia mengetahui"},{"a":"مَنْ","en":"(the One) Who","id":"siapa/apa"},{"a":"خَلَقَ","en":"created","id":"Dia ciptakan"},{"a":"وَهُوَ","en":"And He","id":"dan Dia"},{"a":"ٱللَّطِيفُ","en":"(is) the Subtle","id":"Maha Halus"},{"a":"ٱلْخَبِيرُ","en":"the All-Aware","id":"Maha mengetahui"}]},{"n":15,"key":"67:15","arabic":"هُوَ ٱلَّذِى جَعَلَ لَكُمُ ٱلْأَرْضَ ذَلُولًا فَٱمْشُوا۟ فِى مَنَاكِبِهَا وَكُلُوا۟ مِن رِّزْقِهِۦ ۖ وَإِلَيْهِ ٱلنُّشُورُ","page":563,"juz":29,"en":"It is He who made the earth tame for you - so walk among its slopes and eat of His provision - and to Him is the resurrection.","id":"Dialah yang menjadikan bumi untuk kamu yang mudah dijelajahi, maka jelajahilah di segala penjurunya dan makanlah sebagian dari rezeki-Nya. Dan hanya kepada-Nyalah kamu (kembali setelah) dibangkitkan.","words":[{"a":"هُوَ","en":"He","id":"dan Dia"},{"a":"ٱلَّذِى","en":"(is) the One Who","id":"yang"},{"a":"جَعَلَ","en":"made","id":"menjadikan"},{"a":"لَكُمُ","en":"for you","id":"bagi kalian"},{"a":"ٱلْأَرْضَ","en":"the earth","id":"bumi"},{"a":"ذَلُولًۭا","en":"subservient","id":"mudah dipergunakan"},{"a":"فَٱمْشُوا۟","en":"so walk","id":"maka berjalanlah kamu"},{"a":"فِى","en":"in","id":"di/pada"},{"a":"مَنَاكِبِهَا","en":"(the) paths thereof","id":"segala penjuru"},{"a":"وَكُلُوا۟","en":"and eat","id":"dan makanlah"},{"a":"مِن","en":"of","id":"dari"},{"a":"رِّزْقِهِۦ ۖ","en":"His provision","id":"sebagian rizki-Nya"},{"a":"وَإِلَيْهِ","en":"and to Him","id":"dan kepada-Nya"},{"a":"ٱلنُّشُورُ","en":"(is) the Resurrection","id":"dibangkitkan kembali"}]},{"n":16,"key":"67:16","arabic":"ءَأَمِنتُم مَّن فِى ٱلسَّمَآءِ أَن يَخْسِفَ بِكُمُ ٱلْأَرْضَ فَإِذَا هِىَ تَمُورُ","page":563,"juz":29,"en":"Do you feel secure that He who is above would not cause the earth to swallow you and suddenly it would sway?","id":"Sudah merasa amankah kamu, bahwa Dia yang di langit tidak akan membuat kamu ditelan bumi ketika tiba-tiba ia terguncang?","words":[{"a":"ءَأَمِنتُم","en":"Do you feel secure","id":"apakah kamu merasa aman"},{"a":"مَّن","en":"(from Him) Who","id":"siapa (Allah)"},{"a":"فِى","en":"(is) in","id":"di"},{"a":"ٱلسَّمَآءِ","en":"the heaven","id":"langit"},{"a":"أَن","en":"not","id":"bahwa"},{"a":"يَخْسِفَ","en":"He will cause to swallow","id":"Dia akan membenamkan"},{"a":"بِكُمُ","en":"you","id":"dengan/untuk kalian"},{"a":"ٱلْأَرْضَ","en":"the earth","id":"bumi"},{"a":"فَإِذَا","en":"when","id":"maka tiba-tiba"},{"a":"هِىَ","en":"it","id":"ia/bumi"},{"a":"تَمُورُ","en":"sways","id":"bergoncang"}]},{"n":17,"key":"67:17","arabic":"أَمْ أَمِنتُم مَّن فِى ٱلسَّمَآءِ أَن يُرْسِلَ عَلَيْكُمْ حَاصِبًا ۖ فَسَتَعْلَمُونَ كَيْفَ نَذِيرِ","page":563,"juz":29,"en":"Or do you feel secure that He who is above would not send against you a storm of stones? Then you would know how [severe] was My warning.","id":"atau sudah merasa amankah kamu, bahwa Dia yang di langit tidak akan mengirimkan badai yang berbatu kepadamu? Namun kelak kamu akan mengetahui bagaimana (akibat mendustakan) peringatan-Ku.","words":[{"a":"أَمْ","en":"Or","id":"atau"},{"a":"أَمِنتُم","en":"do you feel secure","id":"kamu merasa aman"},{"a":"مَّن","en":"(from Him) Who","id":"siapa (Allah)"},{"a":"فِى","en":"(is) in","id":"di"},{"a":"ٱلسَّمَآءِ","en":"the heaven","id":"langit"},{"a":"أَن","en":"that","id":"bahwa"},{"a":"يُرْسِلَ","en":"He will send","id":"Dia akan mengirimkan"},{"a":"عَلَيْكُمْ","en":"against you","id":"atas kalian"},{"a":"حَاصِبًۭا ۖ","en":"a storm of stones","id":"angin yang mengandung batu"},{"a":"فَسَتَعْلَمُونَ","en":"Then you would know","id":"maka kelak kamu akan mengetahui"},{"a":"كَيْفَ","en":"how","id":"bagaimana"},{"a":"نَذِيرِ","en":"(was) My warning","id":"peringatan-Ku"}]},{"n":18,"key":"67:18","arabic":"وَلَقَدْ كَذَّبَ ٱلَّذِينَ مِن قَبْلِهِمْ فَكَيْفَ كَانَ نَكِيرِ","page":563,"juz":29,"en":"And already had those before them denied, and how [terrible] was My reproach.","id":"Dan sungguh, orang-orang yang sebelum mereka pun telah mendustakan (rasul-rasul-Nya). Maka betapa hebatnya kemurkaan-Ku!","words":[{"a":"وَلَقَدْ","en":"And indeed","id":"dan sesungguhnya"},{"a":"كَذَّبَ","en":"denied","id":"telah mendustakan"},{"a":"ٱلَّذِينَ","en":"those","id":"orang-orang yang"},{"a":"مِن","en":"from","id":"dari"},{"a":"قَبْلِهِمْ","en":"before them","id":"sebelum mereka"},{"a":"فَكَيْفَ","en":"and how","id":"maka bagaimana"},{"a":"كَانَ","en":"was","id":"adalah ia"},{"a":"نَكِيرِ","en":"My rejection","id":"celaan-Ku/kemurkaan-Ku"}]},{"n":19,"key":"67:19","arabic":"أَوَلَمْ يَرَوْا۟ إِلَى ٱلطَّيْرِ فَوْقَهُمْ صَـٰٓفَّـٰتٍ وَيَقْبِضْنَ ۚ مَا يُمْسِكُهُنَّ إِلَّا ٱلرَّحْمَـٰنُ ۚ إِنَّهُۥ بِكُلِّ شَىْءٍۭ بَصِيرٌ","page":563,"juz":29,"en":"Do they not see the birds above them with wings outspread and [sometimes] folded in? None holds them [aloft] except the Most Merciful. Indeed He is, of all things, Seeing.","id":"Tidakkah mereka memperhatikan burung-burung yang mengembangkan dan mengatupkan sayapnya di atas mereka? Tidak ada yang menahannya (di udara) selain Yang Maha Pengasih. Sungguh, Dia Maha Melihat segala sesuatu.","words":[{"a":"أَوَلَمْ","en":"Do not","id":"ataukah tidak"},{"a":"يَرَوْا۟","en":"they see","id":"mereka memperhatikan"},{"a":"إِلَى","en":"[to]","id":"kepada"},{"a":"ٱلطَّيْرِ","en":"the birds","id":"burung"},{"a":"فَوْقَهُمْ","en":"above them","id":"di atas mereka"},{"a":"صَـٰٓفَّـٰتٍۢ","en":"spreading (their wings)","id":"mengembangkan sayap"},{"a":"وَيَقْبِضْنَ ۚ","en":"and folding","id":"dan ia mengatupkannya"},{"a":"مَا","en":"Not","id":"tidak ada"},{"a":"يُمْسِكُهُنَّ","en":"holds them","id":"yang menahan mereka"},{"a":"إِلَّا","en":"except","id":"kecuali"},{"a":"ٱلرَّحْمَـٰنُ ۚ","en":"the Most Gracious","id":"Maha Pengasih"},{"a":"إِنَّهُۥ","en":"Indeed, He","id":"sesungguhnya Dia"},{"a":"بِكُلِّ","en":"(is) of every","id":"dengan segala"},{"a":"شَىْءٍۭ","en":"thing","id":"sesuatu"},{"a":"بَصِيرٌ","en":"All-Seer","id":"Maha melihat"}]},{"n":20,"key":"67:20","arabic":"أَمَّنْ هَـٰذَا ٱلَّذِى هُوَ جُندٌ لَّكُمْ يَنصُرُكُم مِّن دُونِ ٱلرَّحْمَـٰنِ ۚ إِنِ ٱلْكَـٰفِرُونَ إِلَّا فِى غُرُورٍ","page":563,"juz":29,"en":"Or who is it that could be an army for you to aid you other than the Most Merciful? The disbelievers are not but in delusion.","id":"Atau siapakah yang akan menjadi bala tentara bagimu yang dapat membelamu selain (Allah) Yang Maha Pengasih? Orang-orang kafir itu hanyalah dalam (keadaan) tertipu.","words":[{"a":"أَمَّنْ","en":"Who is","id":"atau siapakah"},{"a":"هَـٰذَا","en":"this","id":"ini"},{"a":"ٱلَّذِى","en":"the one","id":"yang"},{"a":"هُوَ","en":"he","id":"dia"},{"a":"جُندٌۭ","en":"(is) an army","id":"bala tentara"},{"a":"لَّكُمْ","en":"for you","id":"bagi kalian"},{"a":"يَنصُرُكُم","en":"to help you","id":"dia menolongmu"},{"a":"مِّن","en":"from","id":"dari"},{"a":"دُونِ","en":"besides","id":"selain"},{"a":"ٱلرَّحْمَـٰنِ ۚ","en":"the Most Gracious","id":"Maha Pengasih"},{"a":"إِنِ","en":"Not","id":"tidaklah"},{"a":"ٱلْكَـٰفِرُونَ","en":"(are) the disbelievers","id":"orang-orang kafir"},{"a":"إِلَّا","en":"but","id":"kecuali"},{"a":"فِى","en":"in","id":"dalam"},{"a":"غُرُورٍ","en":"delusion","id":"keadaan tertipu"}]},{"n":21,"key":"67:21","arabic":"أَمَّنْ هَـٰذَا ٱلَّذِى يَرْزُقُكُمْ إِنْ أَمْسَكَ رِزْقَهُۥ ۚ بَل لَّجُّوا۟ فِى عُتُوٍّ وَنُفُورٍ","page":563,"juz":29,"en":"Or who is it that could provide for you if He withheld His provision? But they have persisted in insolence and aversion.","id":"Atau siapakah yang dapat memberimu rezeki jika Dia menahan rezeki-Nya? Bahkan mereka terus-menerus dalam kesombongan dan menjauhkan diri (dari kebenaran).","words":[{"a":"أَمَّنْ","en":"Who is","id":"atau siapakah"},{"a":"هَـٰذَا","en":"this","id":"ini"},{"a":"ٱلَّذِى","en":"the one","id":"yang"},{"a":"يَرْزُقُكُمْ","en":"to provide you","id":"memberi rezeki kamu"},{"a":"إِنْ","en":"if","id":"jika"},{"a":"أَمْسَكَ","en":"He withheld","id":"Dia menahan"},{"a":"رِزْقَهُۥ ۚ","en":"His provision","id":"rezekinya"},{"a":"بَل","en":"Nay","id":"bahkan/tetapi"},{"a":"لَّجُّوا۟","en":"they persist","id":"mereka terus-menerus"},{"a":"فِى","en":"in","id":"dalam"},{"a":"عُتُوٍّۢ","en":"pride","id":"kesombongan"},{"a":"وَنُفُورٍ","en":"and aversion","id":"dan lari/berpaling"}]},{"n":22,"key":"67:22","arabic":"أَفَمَن يَمْشِى مُكِبًّا عَلَىٰ وَجْهِهِۦٓ أَهْدَىٰٓ أَمَّن يَمْشِى سَوِيًّا عَلَىٰ صِرَٰطٍ مُّسْتَقِيمٍ","page":563,"juz":29,"en":"Then is one who walks fallen on his face better guided or one who walks erect on a straight path?","id":"Apakah orang yang merangkak dengan wajah tertelungkup yang lebih terpimpin (dalam kebenaran) ataukah orang yang berjalan tegap di atas jalan yang lurus?","words":[{"a":"أَفَمَن","en":"Then is he who","id":"maka apakah orang"},{"a":"يَمْشِى","en":"walks","id":"dia berjalan"},{"a":"مُكِبًّا","en":"fallen","id":"tiarap/telengkup"},{"a":"عَلَىٰ","en":"on","id":"di atas"},{"a":"وَجْهِهِۦٓ","en":"his face","id":"mukanya"},{"a":"أَهْدَىٰٓ","en":"better guided","id":"lebih mendapat petunjuk"},{"a":"أَمَّن","en":"or (he) who","id":"ataukah orang"},{"a":"يَمْشِى","en":"walks","id":"dia berjalan"},{"a":"سَوِيًّا","en":"upright","id":"sama lurus"},{"a":"عَلَىٰ","en":"on","id":"di atas"},{"a":"صِرَٰطٍۢ","en":"(the) Path","id":"jalan"},{"a":"مُّسْتَقِيمٍۢ","en":"Straight","id":"yang lurus"}]},{"n":23,"key":"67:23","arabic":"قُلْ هُوَ ٱلَّذِىٓ أَنشَأَكُمْ وَجَعَلَ لَكُمُ ٱلسَّمْعَ وَٱلْأَبْصَـٰرَ وَٱلْأَفْـِٔدَةَ ۖ قَلِيلًا مَّا تَشْكُرُونَ","page":563,"juz":29,"en":"Say, \"It is He who has produced you and made for you hearing and vision and hearts [i.e., intellect]; little are you grateful.\"","id":"Katakanlah, \"Dialah yang menciptakan kamu dan menjadikan pendengaran, penglihatan dan hati nurani bagi kamu. (Tetapi) sedikit sekali kamu bersyukur.","words":[{"a":"قُلْ","en":"Say","id":"katakanlah"},{"a":"هُوَ","en":"He","id":"Dia"},{"a":"ٱلَّذِىٓ","en":"(is) the One Who","id":"yang"},{"a":"أَنشَأَكُمْ","en":"produced you","id":"menumbuhkan/menciptakan kamu"},{"a":"وَجَعَلَ","en":"and made","id":"dan menjadikan"},{"a":"لَكُمُ","en":"for you","id":"bagi kalian"},{"a":"ٱلسَّمْعَ","en":"the hearing","id":"pendengaran"},{"a":"وَٱلْأَبْصَـٰرَ","en":"and the vision","id":"dan penglihatan"},{"a":"وَٱلْأَفْـِٔدَةَ ۖ","en":"and the feelings","id":"dan hati"},{"a":"قَلِيلًۭا","en":"Little","id":"sedikit"},{"a":"مَّا","en":"(is) what","id":"apa"},{"a":"تَشْكُرُونَ","en":"you give thanks","id":"kalian bersyukur"}]},{"n":24,"key":"67:24","arabic":"قُلْ هُوَ ٱلَّذِى ذَرَأَكُمْ فِى ٱلْأَرْضِ وَإِلَيْهِ تُحْشَرُونَ","page":563,"juz":29,"en":"Say, \"It is He who has multiplied you throughout the earth, and to Him you will be gathered.\"","id":"Katakanlah, \"Dialah yang menjadikan kamu berkembang biak di muka bumi, dan hanya kepada-Nya kamu akan dikumpulkan.\"","words":[{"a":"قُلْ","en":"Say","id":"katakanlah"},{"a":"هُوَ","en":"He","id":"Dia"},{"a":"ٱلَّذِى","en":"(is) the One Who","id":"yang"},{"a":"ذَرَأَكُمْ","en":"multiplied you","id":"menjadikan kamu berkembang biak"},{"a":"فِى","en":"in","id":"di muka"},{"a":"ٱلْأَرْضِ","en":"the earth","id":"bumi"},{"a":"وَإِلَيْهِ","en":"and to Him","id":"dan kepada-Nya"},{"a":"تُحْشَرُونَ","en":"you will be gathered","id":"kamu akan dikumpulkan"}]},{"n":25,"key":"67:25","arabic":"وَيَقُولُونَ مَتَىٰ هَـٰذَا ٱلْوَعْدُ إِن كُنتُمْ صَـٰدِقِينَ","page":563,"juz":29,"en":"And they say, \"When is this promise, if you should be truthful?\"","id":"Dan mereka berkata, \"Kapan (datangnya) ancaman itu jika kamu orang yang benar?\"","words":[{"a":"وَيَقُولُونَ","en":"And they say","id":"dan mereka berkata"},{"a":"مَتَىٰ","en":"When","id":"kapan"},{"a":"هَـٰذَا","en":"(is) this","id":"ini"},{"a":"ٱلْوَعْدُ","en":"promise","id":"janji/ancaman"},{"a":"إِن","en":"if","id":"jika"},{"a":"كُنتُمْ","en":"you are","id":"kalian adalah"},{"a":"صَـٰدِقِينَ","en":"truthful","id":"orang-orang yang benar"}]},{"n":26,"key":"67:26","arabic":"قُلْ إِنَّمَا ٱلْعِلْمُ عِندَ ٱللَّهِ وَإِنَّمَآ أَنَا۠ نَذِيرٌ مُّبِينٌ","page":563,"juz":29,"en":"Say, \"The knowledge is only with Allāh, and I am only a clear warner.\"","id":"Katakanlah (Muhammad), \"Sesungguhnya ilmu (tentang hari Kiamat itu) hanya ada pada Allah. Dan aku hanyalah seorang pemberi peringatan yang menjelaskan.\"","words":[{"a":"قُلْ","en":"Say","id":"katakanlah"},{"a":"إِنَّمَا","en":"Only","id":"sesungguhnya"},{"a":"ٱلْعِلْمُ","en":"the knowledge","id":"pengetahuan"},{"a":"عِندَ","en":"(is) with","id":"di sisi"},{"a":"ٱللَّهِ","en":"Allah","id":"Allah"},{"a":"وَإِنَّمَآ","en":"and only","id":"dan sesungguhnya"},{"a":"أَنَا۠","en":"I am","id":"Aku"},{"a":"نَذِيرٌۭ","en":"a warner","id":"seorang pemberi peringatan"},{"a":"مُّبِينٌۭ","en":"clear","id":"yang nyata"}]},{"n":27,"key":"67:27","arabic":"فَلَمَّا رَأَوْهُ زُلْفَةً سِيٓـَٔتْ وُجُوهُ ٱلَّذِينَ كَفَرُوا۟ وَقِيلَ هَـٰذَا ٱلَّذِى كُنتُم بِهِۦ تَدَّعُونَ","page":564,"juz":29,"en":"But when they see it approaching, the faces of those who disbelieve will be distressed, and it will be said, \"This is that for which you used to call.\"","id":"Maka ketika mereka melihat azab (pada hari Kiamat) sudah dekat, wajah orang-orang kafir itu menjadi muram. Dan dikatakan (kepada mereka), \"Inilah (azab) yang dahulu kamu memintanya.\"","words":[{"a":"فَلَمَّا","en":"But when","id":"maka ketika"},{"a":"رَأَوْهُ","en":"they (will) see it","id":"mereka melihatnya (azab)"},{"a":"زُلْفَةًۭ","en":"approaching","id":"dekat"},{"a":"سِيٓـَٔتْ","en":"(will be) distressed","id":"menjadi buruk/jelek"},{"a":"وُجُوهُ","en":"(the) faces","id":"muka-muka"},{"a":"ٱلَّذِينَ","en":"(of) those who","id":"orang-orang yang"},{"a":"كَفَرُوا۟","en":"disbelieved","id":"kafir/ingkar"},{"a":"وَقِيلَ","en":"and it will be said","id":"dan dikatakan"},{"a":"هَـٰذَا","en":"This","id":"ini"},{"a":"ٱلَّذِى","en":"(is) that which","id":"yang"},{"a":"كُنتُم","en":"you used to","id":"kalian adalah"},{"a":"بِهِۦ","en":"for it","id":"dengannya"},{"a":"تَدَّعُونَ","en":"call","id":"kamu meminta"}]},{"n":28,"key":"67:28","arabic":"قُلْ أَرَءَيْتُمْ إِنْ أَهْلَكَنِىَ ٱللَّهُ وَمَن مَّعِىَ أَوْ رَحِمَنَا فَمَن يُجِيرُ ٱلْكَـٰفِرِينَ مِنْ عَذَابٍ أَلِيمٍ","page":564,"juz":29,"en":"Say, [O Muḥammad], \"Have you considered: whether Allāh should cause my death and those with me or have mercy upon us, who can protect the disbelievers from a painful punishment?\"","id":"Katakanlah (Muhammad), \"Tahukah kamu jika Allah mematikan aku dan orang-orang yang bersamaku atau memberi rahmat kepada kami, (maka kami akan masuk surga), lalu siapa yang dapat melindungi orang-orang kafir dari azab yang pedih?\"","words":[{"a":"قُلْ","en":"Say","id":"katakanlah"},{"a":"أَرَءَيْتُمْ","en":"Have you seen","id":"adakah kamu perhatikan"},{"a":"إِنْ","en":"if","id":"jika"},{"a":"أَهْلَكَنِىَ","en":"destroys me","id":"membinasakan aku"},{"a":"ٱللَّهُ","en":"Allah","id":"Allah"},{"a":"وَمَن","en":"and whoever","id":"dan orang-orang yang"},{"a":"مَّعِىَ","en":"(is) with me","id":"bersamaku"},{"a":"أَوْ","en":"or","id":"atau"},{"a":"رَحِمَنَا","en":"has mercy upon us","id":"Dia memberi rahmat kami"},{"a":"فَمَن","en":"then who","id":"maka barang siapa"},{"a":"يُجِيرُ","en":"(can) protect","id":"menolong/melindungi"},{"a":"ٱلْكَـٰفِرِينَ","en":"the disbelievers","id":"orang-orang yang kafir"},{"a":"مِنْ","en":"from","id":"dari"},{"a":"عَذَابٍ","en":"a punishment","id":"azab"},{"a":"أَلِيمٍۢ","en":"painful","id":"yang pedih"}]},{"n":29,"key":"67:29","arabic":"قُلْ هُوَ ٱلرَّحْمَـٰنُ ءَامَنَّا بِهِۦ وَعَلَيْهِ تَوَكَّلْنَا ۖ فَسَتَعْلَمُونَ مَنْ هُوَ فِى ضَلَـٰلٍ مُّبِينٍ","page":564,"juz":29,"en":"Say, \"He is the Most Merciful; we have believed in Him, and upon Him we have relied. And you will [come to] know who it is that is in clear error.\"","id":"Katakanlah, \"Dialah Yang Maha Pengasih, kami beriman kepada-Nya dan kepada-Nya kami bertawakal. Maka kelak kamu akan tahu siapa yang berada dalam kesesatan yang nyata.\"","words":[{"a":"قُلْ","en":"Say","id":"katakanlah"},{"a":"هُوَ","en":"He","id":"Dia"},{"a":"ٱلرَّحْمَـٰنُ","en":"(is) the Most Gracious","id":"Maha Pengasih"},{"a":"ءَامَنَّا","en":"we believe","id":"kami beriman"},{"a":"بِهِۦ","en":"in Him","id":"kepada-Nya"},{"a":"وَعَلَيْهِ","en":"and upon Him","id":"dan atas-Nya"},{"a":"تَوَكَّلْنَا ۖ","en":"we put (our) trust","id":"kami bertawakal"},{"a":"فَسَتَعْلَمُونَ","en":"So you will know","id":"maka kelak kamu akan mengetahuinya"},{"a":"مَنْ","en":"who","id":"siapa"},{"a":"هُوَ","en":"(is) it","id":"dia"},{"a":"فِى","en":"(that is) in","id":"dalam"},{"a":"ضَلَـٰلٍۢ","en":"error","id":"kesesatan"},{"a":"مُّبِينٍۢ","en":"clear","id":"nyata"}]},{"n":30,"key":"67:30","arabic":"قُلْ أَرَءَيْتُمْ إِنْ أَصْبَحَ مَآؤُكُمْ غَوْرًا فَمَن يَأْتِيكُم بِمَآءٍ مَّعِينٍۭ","page":564,"juz":29,"en":"Say, \"Have you considered: if your water was to become sunken [into the earth], then who could bring you flowing water?\"","id":"Katakanlah (Muhammad), \"Terangkanlah kepadaku jika sumber air kamu menjadi kering; maka siapa yang akan memberimu air yang mengalir?\"","words":[{"a":"قُلْ","en":"Say","id":"katakanlah"},{"a":"أَرَءَيْتُمْ","en":"Have you seen","id":"adakah kamu perhatikan"},{"a":"إِنْ","en":"if","id":"jika"},{"a":"أَصْبَحَ","en":"becomes","id":"menjadi"},{"a":"مَآؤُكُمْ","en":"your water","id":"air kamu"},{"a":"غَوْرًۭا","en":"sunken","id":"masuk dalam tanah kering"},{"a":"فَمَن","en":"then who","id":"maka siapa"},{"a":"يَأْتِيكُم","en":"could bring you","id":"mendatangkan kepadamu"},{"a":"بِمَآءٍۢ","en":"water","id":"dengan air"},{"a":"مَّعِينٍۭ","en":"flowing","id":"mata air/mengalir"}]}]}